{
      "button":[
      {
           "name":"Hi!",
           "sub_button":[
            {
               "type":"click",
               "name":"办卡",
               "key":"unicomCard"
            }
            ]
       },
       {
           "name":"约吗?",
           "sub_button":[
            {
               "type":"click",
               "name":"调戏",
               "key":"tuling"
            }]
       },
       {
           "name":"不约",
           "sub_button":[
            {
               "type":"click",
               "name":"课表",
               "key":"schedule"
            }]
       }]
 }
//http://123.57.221.18/mobile_intro
//http://123.57.221.18/mobile_login
//http://123.57.221.18/ranking
//
//{
//      "button":[
//      {
//           "name":"日常事务",
//           "sub_button":[
//            {
//               "type":"view",
//               "name":"出国（境）办理",
//               "url":"http://xb.seu.edu.cn/f3/d7/c6343a62423/page.htm"
//            },
//            {
//                "type":"view",
//                "name":"退宿办理",
//                "url":"http://xb.seu.edu.cn/f4/5a/c6358a62554/page.htm"
//            },
//            {
//               "type":"click",
//               "name":"休、退、复、转",
//               "key":"information"
//            },
//            {
//                "type":"click",
//                "name":"请销假办理",
//                "key":"information"
//            }
//            ]
//       },
//
//       {
//           "name":"资助管理",
//           "sub_button":[
//            {
//               "type":"view",
//               "name":"国家助学贷款管理",
//               "url":"http://xb.seu.edu.cn/f3/e1/c6343a62433/page.htm"
//            },
//            {
//                "type":"view",
//                "name":"生源地助学贷款",
//                "url":"http://xb.seu.edu.cn/f3/e2/c6343a62434/page.htm"
//            },
//            {
//                "type":"click",
//                "name":"资助育人活动",
//                "key":"information"
//            },
//            {
//               "type":"click",
//               "name":"勤工助学",
//               "key":"zhu_list"
//            },
//            {
//                "type":"click",
//                "name":"我的勤工助学",
//                "key":"zhu_querry"
//            }]
//       },
//       {
//           "name":"新生资助",
//           "sub_button":[
//            {
//               "type":"view",
//               "name":"绿色通道",
//               "url":"http://mp.weixin.qq.com/s?__biz=MzAxMzExMTAwMw==&mid=210557150&idx=1&sn=eda60a19c8ed359138973a1a626904eb#rd"
//            },
//            {
//                "type":"view",
//                "name":"励志典型",
//                "url":"http://mp.weixin.qq.com/s?__biz=MzAxMzExMTAwMw==&mid=210557150&idx=1&sn=eda60a19c8ed359138973a1a626904eb#rd"
//            },
//            {
//                "type":"click",
//                "name":"资助政策",
//                "key":"information"
//            },
//            {
//               "type":"click",
//               "name":"学生社团",
//               "key":"information"
//            },
//            {
//                "type":"click",
//                "name":"其他",
//                "key":"information"
//            }]
//       }]
// }